{
    "rooms": [
        {
            "id": 1,
            "name": "Entree",
            "type": "entrance",
            "walls_surface_m2": 12.48,
            "area_m2": 3.26,
            "wall_treatments": {
                "sanding_filling": false,
                "priming": false,
                "one_coat": false,
                "two_coats": false
            },
            "ceiling_treatments": {
                "sanding_filling": false,
                "priming": false,
                "one_coat": false,
                "two_coats": false
            }
        },
        {
            "id": 2,
            "name": "Eetkamer",
            "type": "dining room",
            "walls_surface_m2": 23.76,
            "area_m2": 9.28,
            "wall_treatments": {
                "sanding_filling": false,
                "priming": false,
                "one_coat": false,
                "two_coats": false
            },
            "ceiling_treatments": {
                "sanding_filling": false,
                "priming": false,
                "one_coat": false,
                "two_coats": false
            }
        },
        {
            "id": 3,
            "name": "Woonkamer",
            "type": "living room",
            "walls_surface_m2": 25.92,
            "area_m2": 11.97,
            "wall_treatments": {
                "sanding_filling": false,
                "priming": false,
                "one_coat": false,
                "two_coats": false
            },
            "ceiling_treatments": {
                "sanding_filling": false,
                "priming": false,
                "one_coat": false,
                "two_coats": false
            }
        },
        {
            "id": 4,
            "name": "Keuken",
            "type": "kitchen",
            "walls_surface_m2": 15.84,
            "area_m2": 5.28,
            "wall_treatments": {
                "sanding_filling": false,
                "priming": false,
                "one_coat": false,
                "two_coats": false
            },
            "ceiling_treatments": {
                "sanding_filling": false,
                "priming": false,
                "one_coat": false,
                "two_coats": false
            }
        },
        {
            "id": 5,
            "name": "Zijkamer",
            "type": "side room",
            "walls_surface_m2": 21.36,
            "area_m2": 8.42,
            "wall_treatments": {
                "sanding_filling": false,
                "priming": false,
                "one_coat": false,
                "two_coats": false
            },
            "ceiling_treatments": {
                "sanding_filling": false,
                "priming": false,
                "one_coat": false,
                "two_coats": false
            }
        },
        {
            "id": 6,
            "name": "Slaapkamer 1",
            "type": "bedroom 1",
            "walls_surface_m2": 21.6,
            "area_m2": 8.1,
            "wall_treatments": {
                "sanding_filling": false,
                "priming": false,
                "one_coat": false,
                "two_coats": false
            },
            "ceiling_treatments": {
                "sanding_filling": false,
                "priming": false,
                "one_coat": false,
                "two_coats": false
            }
        },
        {
            "id": 7,
            "name": "Slaapkamer 2",
            "type": "bedroom 2",
            "walls_surface_m2": 20.16,
            "area_m2": 7.56,
            "wall_treatments": {
                "sanding_filling": false,
                "priming": false,
                "one_coat": false,
                "two_coats": false
            },
            "ceiling_treatments": {
                "sanding_filling": false,
                "priming": false,
                "one_coat": false,
                "two_coats": false
            }
        },
        {
            "id": 8,
            "name": "Badkamer",
            "type": "bathroom",
            "walls_surface_m2": 14.4,
            "area_m2": 3.6,
            "wall_treatments": {
                "sanding_filling": false,
                "priming": false,
                "one_coat": false,
                "two_coats": false
            },
            "ceiling_treatments": {
                "sanding_filling": false,
                "priming": false,
                "one_coat": false,
                "two_coats": false
            }
        },
        {
            "id": 9,
            "name": "Waskamer",
            "type": "laundry room",
            "walls_surface_m2": 15.36,
            "area_m2": 4.32,
            "wall_treatments": {
                "sanding_filling": false,
                "priming": false,
                "one_coat": false,
                "two_coats": false
            },
            "ceiling_treatments": {
                "sanding_filling": false,
                "priming": false,
                "one_coat": false,
                "two_coats": false
            }
        },
        {
            "id": 10,
            "name": "Hal",
            "type": "hall",
            "walls_surface_m2": 10.56,
            "area_m2": 2.64,
            "wall_treatments": {
                "sanding_filling": false,
                "priming": false,
                "one_coat": false,
                "two_coats": false
            },
            "ceiling_treatments": {
                "sanding_filling": false,
                "priming": false,
                "one_coat": false,
                "two_coats": false
            }
        }
    ],
    "notes": "Generated from AI analysis with total wall area per room",
    "analysis_timestamp": "2025-08-06T23:04:47.229356",
    "fresh_analysis": true
}